GANSM/__init__.py
GANSM/main.py
GANSM-0.1.1.dist-info/METADATA
GANSM-0.1.1.dist-info/WHEEL
GANSM-0.1.1.dist-info/top_level.txt
GANSM-0.1.1.dist-info/RECORD
