Metadata-Version: 2.1
Name: GANSM
Version: 0.1.1
Requires-Dist: torch>=1.9.0
Requires-Dist: torchvision>=0.10.0
Requires-Dist: tensorboard>=2.5.0
